fosDB/__init__.py
fosDB/__main__.py
fosDB/models.py
limes/__init__.py
limes/__main__.py
limes/limes.py
limes/res/__init__.py
limes/res/strings.py
limes/tools/__init__.py
limes/tools/qol.py
limes_common/__init__.py
limes_common/config.py
limes_common/exceptions.py
limes_common/utils.py
limes_common/connections/__init__.py
limes_common/connections/http.py
limes_common/connections/ssh.py
limes_common/connections/statics/__init__.py
limes_common/connections/statics/eLab.py
limes_common/connections/statics/server.py
limes_common/models/__init__.py
limes_common/models/basic.py
limes_common/models/network/__init__.py
limes_common/models/network/elab.py
limes_common/models/network/endpoints.py
limes_common/models/network/http.py
limes_common/models/network/provider.py
limes_common/models/network/server.py
limes_core/__init__.py
limes_core/apps.py
limes_core/fileHandler.py
limes_core/providers.py
limes_core/urls.py
limes_core/views.py
limes_core/migrations/__init__.py
limes_server/__init__.py
limes_server/gunicorn.conf.py
limes_server/settings.py
limes_server/urls.py
limes_server/wsgi.py
tests/__init__.py
tests/__main__.py
tests/limes.py
tests/models.py
tests/network.py
tests/sshConnection.py
tests/testTools.py
limes_server-0.2.dev1.dist-info/LICENSE
limes_server-0.2.dev1.dist-info/METADATA
limes_server-0.2.dev1.dist-info/WHEEL
limes_server-0.2.dev1.dist-info/top_level.txt
limes_server-0.2.dev1.dist-info/RECORD
