Metadata-Version: 2.1
Name: limes-server
Version: 0.2.dev1
Summary: limes core test package
Home-page: https://github.com/Tony-xy-Liu/Limes
Author: Tony Liu
Author-email: contactTonyLiu@gmail.com
License: UNKNOWN
Project-URL: Bug Tracker, https://github.com/Tony-xy-Liu/Limes/issues
Platform: UNKNOWN
Classifier: Programming Language :: Python :: 3.9
Classifier: License :: OSI Approved :: BSD License
Classifier: Operating System :: OS Independent
Requires-Python: >=3.9
License-File: LICENSE
Requires-Dist: requests
Requires-Dist: django
